photoshop/__init__.py
photoshop/api.py
photoshop/crypto.py
photoshop/photoshop_connection.py
photoshop/protocol.py
photoshop/api/networkEventSubscribe.js.j2
photoshop/api/networkEventUnsubscribe.js.j2
photoshop/api/open.js.j2
photoshop/api/sendDocumentInfoToNetworkClient.js.j2
photoshop/api/sendDocumentStreamToNetworkClient.js.j2
photoshop/api/sendDocumentThumbnailToNetworkClient.js.j2
photoshop/api/sendLayerShapeToNetworkClient.js.j2
photoshop/api/sendLayerThumbnailToNetworkClient.js.j2
photoshop_connection-0.3.0.dist-info/METADATA
photoshop_connection-0.3.0.dist-info/WHEEL
photoshop_connection-0.3.0.dist-info/licenses/LICENSE
photoshop_connection-0.3.0.dist-info/RECORD
