Metadata-Version: 2.4
Name: photoshop-connection
Version: 0.3.0
Summary: Python package for Photoshop Connection
Project-URL: Repository, https://github.com/kyamagu/photoshop-connection
Project-URL: Documentation, https://photoshop-connection.readthedocs.io
Author-email: Kota Yamaguchi <KotaYamaguchi1984@gmail.com>
License-Expression: MIT
License-File: LICENSE
Classifier: Development Status :: 4 - Beta
Classifier: Intended Audience :: Developers
Classifier: Programming Language :: Python
Classifier: Topic :: Multimedia :: Graphics
Classifier: Topic :: Software Development :: Libraries
Requires-Python: <3.14,>3.9.1
Requires-Dist: cryptography>=44.0
Requires-Dist: jinja2>=3.0
Requires-Dist: pillow>=10.0
Provides-Extra: eslint
Requires-Dist: esprima>=4.0; extra == 'eslint'
